smacc/__init__.py
smacc/__main__.py
smacc/config.py
smacc/gui.py
smacc/utils.py
smacc-0.0.4.dist-info/METADATA
smacc-0.0.4.dist-info/WHEEL
smacc-0.0.4.dist-info/top_level.txt
smacc-0.0.4.dist-info/RECORD
