Metadata-Version: 2.1
Name: smacc
Version: 0.0.4
Summary: Sleep manipulation and communication clickything
Home-page: https://github.com/remrama/smacc
Author: Remington Mallett
Author-email: mallett.remy@gmail.com
Project-URL: Homepage, https://github.com/remrama/smacc
Project-URL: Source, https://github.com/remrama/smacc
Project-URL: Bug Tracker, https://github.com/remrama/smacc/issues
Project-URL: Release Notes, https://github.com/remrama/smacc/releases
Classifier: Environment :: Console
Classifier: Operating System :: OS Independent
Classifier: License :: OSI Approved :: BSD License
Classifier: Programming Language :: Python :: 3
Classifier: Intended Audience :: Science/Research
Requires-Python: ==3.8.*
Requires-Dist: numpy
Requires-Dist: PyQt5
Requires-Dist: scipy
Provides-Extra: port_triggers
Requires-Dist: psychopy ; extra == 'port_triggers'
